LICENSE
MANIFEST.in
README.md
setup.py
tree_menu/__init__.py
tree_menu/admin.py
tree_menu/apps.py
tree_menu/models.py
tree_menu/tests.py
tree_menu/urls.py
tree_menu/views.py
tree_menu322.egg-info/PKG-INFO
tree_menu322.egg-info/SOURCES.txt
tree_menu322.egg-info/dependency_links.txt
tree_menu322.egg-info/requires.txt
tree_menu322.egg-info/top_level.txt
tree_menu/migrations/0001_initial.py
tree_menu/migrations/__init__.py
tree_menu/templates/tree_menu/menu.html
tree_menu/templates/tree_menu/menu_item.html
tree_menu/templates/tree_menu/test.html
tree_menu/templatetags/menu_tags.py
tree_menu/templatetags/__pycache__/menu_tags.cpython-311.pyc
tree_menu/templatetags/__pycache__/menu_tags.cpython-312.pyc